interleaved/__init__.py
interleaved/__main__.py
interleaved/core/__init__.py
interleaved/tests/__init__.py
interleaved/tests/test_1984.py
interleaved-0.0.0.dev0.dist-info/licenses/LICENSE.txt
interleaved-0.0.0.dev0.dist-info/METADATA
interleaved-0.0.0.dev0.dist-info/WHEEL
interleaved-0.0.0.dev0.dist-info/top_level.txt
interleaved-0.0.0.dev0.dist-info/RECORD
