Metadata-Version: 2.4
Name: interleaved
Version: 0.0.0.dev0
Summary: interleaved
Author-email: Johannes <johannes-programming@mailfence.com>
License: The MIT License (MIT)
Project-URL: Download, https://pypi.org/project/interleaved/#files
Project-URL: Index, https://pypi.org/project/interleaved/
Project-URL: Source, https://github.com/johannes-programming/interleaved/
Classifier: Development Status :: 1 - Planning
Classifier: License :: OSI Approved :: MIT License
Classifier: Natural Language :: English
Classifier: Operating System :: OS Independent
Classifier: Programming Language :: Python
Classifier: Programming Language :: Python :: 3
Classifier: Programming Language :: Python :: 3 :: Only
Classifier: Typing :: Typed
Requires-Python: >=3.11
License-File: LICENSE.txt
Dynamic: license-file
